tui_toolkit/__init__.py
tui_toolkit/core.py
tui_toolkit/list.py
tui_toolkit/table.py
tui_toolkit/text.py
tui_toolkit-0.2.2.dist-info/METADATA
tui_toolkit-0.2.2.dist-info/WHEEL
tui_toolkit-0.2.2.dist-info/RECORD
