Metadata-Version: 2.1
Name: tui-toolkit
Version: 0.2.2
Summary: 
License: MIT
Author: Simon Redding
Author-email: s1m0n.r3dd1ng@gmail.com
Requires-Python: >=3.11,<4.0
Classifier: License :: OSI Approved :: MIT License
Classifier: Programming Language :: Python :: 3
Classifier: Programming Language :: Python :: 3.11
Requires-Dist: blessed (>=1.20.0,<2.0.0)
Requires-Dist: pytest-cov (>=4.1.0,<5.0.0)
Requires-Dist: tabulate (>=0.9.0,<0.10.0)
